{
  "graph_id": "0018-0045",
  "volume": "iii",
  "chapter": "differentiation",
  "section": "mean-value-theorem",
  "term": "thm:mean-value-theorem",
  "kind": "Theorem",
  "title": "Mean Value Theorem",
  "root": "",
  "statement": "Let $a, b \\in \\mathbb{R}$ with $a < b$. Suppose that $f : [a,b] \\to \\mathbb{R}$ is continuous on $[a,b]$ and differentiable on $(a,b)$. Then there exists $c \\in (a,b)$ such that\n\\[\nf'(c) = \\frac{f(b) - f(a)}{b - a}.\n\\]",
  "current_dependencies": [
    {
      "id": "def:derivative-at-a-point",
      "title": "Derivative at a Point",
      "kind": "Definition",
      "root": ""
    },
    {
      "id": "thm:rolles-theorem",
      "title": "Rolle's Theorem",
      "kind": "Theorem",
      "root": ""
    }
  ]
}