{
  "graph_id": "0015-0029",
  "volume": "iii",
  "chapter": "real-analysis",
  "section": "modulus",
  "term": "thm:absolute-value-symmetric",
  "kind": "Theorem",
  "title": "Absolute Value Is Symmetric",
  "root": "",
  "statement": "For all $a \\in \\mathbb{R}$,\n\\[\n \\lvert -a \\rvert = \\lvert a \\rvert.\n\\]",
  "current_dependencies": [
    {
      "id": "def:absolute-value",
      "title": "Absolute Value",
      "kind": "Definition",
      "root": ""
    },
    {
      "id": "thm:ring-double-negation",
      "title": "Ring Double Negation",
      "kind": "Theorem",
      "root": ""
    }
  ]
}