{
  "graph_id": "0019-0027",
  "volume": "iii",
  "chapter": "continuity",
  "section": "monotone-functions",
  "term": "def:limsup-liminf-function",
  "kind": "Definition",
  "title": "Limits Superior and Inferior of a Function",
  "root": "",
  "statement": "Let $f:E\\to\\mathbb{R}$ and let $x_0$ be an accumulation point of $E$. For each $\\delta>0$ set\n\\[\nU(\\delta)=\\{\\,f(x): x\\in E,\\ 0<|x-x_0|<\\delta\\,\\}.\n\\]\nThe extended real numbers $\\limsup_{x\\to x_0} f(x)$ and $\\liminf_{x\\to x_0} f(x)$ are defined by\n\\[\n\\limsup_{x\\to x_0} f(x)=\\inf_{\\delta>0}\\sup U(\\delta),\n\\qquad\n\\liminf_{x\\to x_0} f(x)=\\sup_{\\delta>0}\\inf U(\\delta),\n\\]\nwhere each inner supremum or infimum is taken in $\\overline{\\mathbb{R}}$ and the outer infimum or supremum ranges over all $\\delta>0$.",
  "current_dependencies": [
    {
      "id": "def:epsilon-neighbourhood",
      "title": "$ $-Neighbourhood",
      "kind": "Definition",
      "root": ""
    },
    {
      "id": "def:function",
      "title": "Function",
      "kind": "Definition",
      "root": ""
    },
    {
      "id": "def:infimum",
      "title": "Infimum",
      "kind": "Definition",
      "root": ""
    },
    {
      "id": "def:supremum",
      "title": "Supremum",
      "kind": "Definition",
      "root": ""
    }
  ]
}