{
  "graph_id": "0011-0001",
  "volume": "vi",
  "chapter": "algebraic-structures",
  "section": "algebraic-structures",
  "term": "def:abelian-group",
  "kind": "Definition",
  "title": "Abelian Group",
  "root": "",
  "statement": "A group $(G,\\star)$ is \\textbf{abelian} if its operation is commutative:\n\\[\n\\forall a,b \\in G,\\quad a\\star b=b\\star a.\n\\]",
  "current_dependencies": [
    {
      "id": "def:commutativity",
      "title": "Commutativity",
      "kind": "Definition",
      "root": ""
    },
    {
      "id": "def:group",
      "title": "Group",
      "kind": "Definition",
      "root": ""
    }
  ]
}