{
  "graph_id": "0005-0011",
  "volume": "viii",
  "chapter": "ordinary-differential-equations",
  "section": "differential-equations-models",
  "term": "def:ordinary-differential-equations-terminology-autonomous-differential-equation",
  "kind": "Definition",
  "title": "Autonomous Differential Equation",
  "root": "",
  "statement": "An \\textbf{autonomous differential equation} is a differential equation in which the independent variable does not appear explicitly.\n\nFor a first-order ordinary differential equation, an autonomous equation has the form\n\\[\ny'=f(y),\n\\]\nwhere the rate of change of $y$ depends only on the current value of $y$, not directly on time $t$.",
  "current_dependencies": []
}