{
  "graph_id": "0025-0037",
  "volume": "ii",
  "chapter": "peano-systems",
  "section": "recursion-on-peano-systems",
  "term": "lem:uniqueness-of-iterator-functions",
  "kind": "Lemma",
  "title": "Uniqueness of Iterator Functions",
  "root": "",
  "statement": "Let $(P,S,1)$ be a Peano system, and let $(W,c,g)$ be iterator data for it. If\n$f,h:P\\to W$ satisfy\n\\[\nf(1)=c,\\qquad h(1)=c,\n\\]\nand\n\\[\n\\forall n\\in P\\;(f(S(n))=g(f(n)))\n\\qquad\\text{and}\\qquad\n\\forall n\\in P\\;(h(S(n))=g(h(n))),\n\\]\nthen $f=h$.",
  "current_dependencies": [
    {
      "id": "def:iterator-data-on-peano-system",
      "title": "Iterator Data",
      "kind": "Definition",
      "root": ""
    },
    {
      "id": "thm:induction-principle-for-peano-system",
      "title": "Induction Principle for a Peano System",
      "kind": "Theorem",
      "root": ""
    }
  ]
}