{
  "graph_id": "0014-0031",
  "volume": "iii",
  "chapter": "sequences",
  "section": "convergence",
  "term": "def:pointwise-negation-sequence",
  "kind": "Definition",
  "title": "Pointwise Negation of a Sequence",
  "root": "",
  "statement": "Let $(x_n)$ be a real sequence. The \\textbf{pointwise negation} of\n$(x_n)$ is the real sequence $(-x_n)$ defined by\n\\[\n(-x)_n := -x_n\n\\qquad\n\\text{for every } n\\in\\mathbb{N}.\n\\]",
  "current_dependencies": [
    {
      "id": "def:scalar-multiple-sequence",
      "title": "Scalar Multiple of a Sequence",
      "kind": "Definition",
      "root": ""
    }
  ]
}