{
  "graph_id": "0032-0016",
  "volume": "i",
  "chapter": "sets-relations-functions",
  "section": "equivalence",
  "term": "lem:rep-independence",
  "kind": "Lemma",
  "title": "Representative Independence Lemma",
  "root": "",
  "statement": "Let $R$ be an equivalence relation on $A$. For any $a,b \\in A$,\n\\[\n[a] = [b]\n\\;\\;\\Longleftrightarrow\\;\\;\n(a,b) \\in R.\n\\]",
  "current_dependencies": [
    {
      "id": "def:equiv-class",
      "title": "Equivalence Class",
      "kind": "Definition",
      "root": ""
    },
    {
      "id": "def:equivalence-relation",
      "title": "Equivalence Relation",
      "kind": "Definition",
      "root": ""
    },
    {
      "id": "def:partition",
      "title": "Partition",
      "kind": "Definition",
      "root": ""
    },
    {
      "id": "def:quotient-set",
      "title": "Quotient Set",
      "kind": "Definition",
      "root": ""
    }
  ]
}